MANIFEST.in
README.md
setup.cfg
setup.py
mattapi/__init__.py
mattapi/targets/__init__.py
mattapi/targets/firefox/__init__.py
mattapi/targets/firefox/bug_manager.py
mattapi/targets/firefox/errors.py
mattapi/targets/firefox/fx_testcase.py
mattapi/targets/firefox/main.py
mattapi/targets/firefox/settings.py
mattapi/targets/firefox/test_dependencies.py
mattapi/targets/firefox/firefox_app/__init__.py
mattapi/targets/firefox/firefox_app/fx_browser.py
mattapi/targets/firefox/firefox_app/fx_collection.py
mattapi/targets/firefox/firefox_app/profiles/.DS_Store
mattapi/targets/firefox/firefox_app/profiles/like_new.zip
mattapi/targets/firefox/firefox_app/profiles/ten_bookmarks.zip
mattapi/targets/firefox/firefox_ui/__init__.py
mattapi/targets/firefox/firefox_ui/about_addons.py
mattapi/targets/firefox/firefox_ui/about_config.py
mattapi/targets/firefox/firefox_ui/about_preferences.py
mattapi/targets/firefox/firefox_ui/bookmarks.py
mattapi/targets/firefox/firefox_ui/content_blocking.py
mattapi/targets/firefox/firefox_ui/content_blocking_tour.py
mattapi/targets/firefox/firefox_ui/customize.py
mattapi/targets/firefox/firefox_ui/docker.py
mattapi/targets/firefox/firefox_ui/download_dialog.py
mattapi/targets/firefox/firefox_ui/download_manager.py
mattapi/targets/firefox/firefox_ui/find_toolbar.py
mattapi/targets/firefox/firefox_ui/general_test_utils.py
mattapi/targets/firefox/firefox_ui/hamburger.py
mattapi/targets/firefox/firefox_ui/history.py
mattapi/targets/firefox/firefox_ui/library.py
mattapi/targets/firefox/firefox_ui/library_menu.py
mattapi/targets/firefox/firefox_ui/location_bar.py
mattapi/targets/firefox/firefox_ui/menu_bar.py
mattapi/targets/firefox/firefox_ui/menus.py
mattapi/targets/firefox/firefox_ui/more_tools.py
mattapi/targets/firefox/firefox_ui/nav_bar.py
mattapi/targets/firefox/firefox_ui/private_window.py
mattapi/targets/firefox/firefox_ui/sidebar.py
mattapi/targets/firefox/firefox_ui/tabs.py
mattapi/targets/firefox/firefox_ui/test_utils.py
mattapi_targets.egg-info/PKG-INFO
mattapi_targets.egg-info/SOURCES.txt
mattapi_targets.egg-info/dependency_links.txt
mattapi_targets.egg-info/entry_points.txt
mattapi_targets.egg-info/not-zip-safe
mattapi_targets.egg-info/requires.txt
mattapi_targets.egg-info/top_level.txt