Metadata-Version: 2.1
Name: mattapi-targets
Version: 0.77
Summary: Targets for Mozilla Iris
Home-page: https://github.com/mwxfr/mattapi.targets
Author: Matt Wobensmith
Author-email: itsmatt@pacbell.net
License: MPL2
Download-URL: https://github.com/mwxfr/mattapi.targets/latest.tar.gz
Keywords: automation,testing
Platform: UNKNOWN
Classifier: Environment :: Console
Classifier: Development Status :: 4 - Beta
Classifier: Intended Audience :: Developers
Classifier: License :: OSI Approved :: Mozilla Public License 2.0 (MPL 2.0)
Classifier: Natural Language :: English
Classifier: Operating System :: MacOS :: MacOS X
Classifier: Operating System :: Microsoft :: Windows :: Windows 10
Classifier: Operating System :: Microsoft :: Windows :: Windows 7
Classifier: Operating System :: Microsoft :: Windows :: Windows 8
Classifier: Operating System :: Microsoft :: Windows :: Windows 8.1
Classifier: Operating System :: POSIX :: Linux
Classifier: Programming Language :: Python :: 3.7
Classifier: Topic :: Software Development :: Quality Assurance
Classifier: Topic :: Software Development :: Testing
Requires-Python: >=3.7.3
Provides-Extra: dev
